[
  {
    "idx": 1,
    "category": "패션 아이템",
    "date": "2025.01.06",
    "title": "1월에 신는 후끈한 슬리퍼",
    "article": ""
  },
  {
    "idx": 2,
    "category": "패션 트렌드",
    "date": "2024.12.19",
    "title": "2025년, 마음속 한자리를 차지할 색 조합 5",
    "article": ""
  },
  {
    "idx": 3,
    "category": "Culture",
    "date": "2025.01.08",
    "title": "‘보그 살롱: 한복’ 이벤트에 초대합니다!",
    "article": ""
  },
  {
    "idx": 4,
    "category": "패션 아이템",
    "date": "2024.12.16",
    "title": "2025년을 뒤흔들 팬츠 스타일 5",
    "article": ""
  },
  {
    "idx": 5,
    "category": "패션 뉴스",
    "date": "2024.12.26",
    "title": "브랜드 앰배서더 게임이 어느 때보다 치열한 이유",
    "article": ""
  },
  {
    "idx": 6,
    "category": "리빙",
    "date": "2025.01.03",
    "title": "새해에는 새로운 마음가짐을! 옷장 정리의 9단계",
    "article": ""
  },
  {
    "idx": 7,
    "category": "뷰티 화보",
    "date": "2025.01.03",
    "title": "나나, 그 유일의 빛깔",
    "article": ""
  },
  {
    "idx": 8,
    "category": "워치&주얼리",
    "date": "2025.01.24",
    "title": "불가리와 김지원의 우아한 랑데부",
    "article": "베이비 페이스의 김지원이 연출한 ‘세르펜티’의 격렬함! 페어 셰이프 브릴리언트 컷 에메랄드 2개와 다이아몬드를 파베 세팅한 화이트 골드 목걸이.^“불가리 스토어에 방문할 때마다 아주 기뻤어요. 그보다 높이 뛰어오르고 그와 사랑에 빠졌답니다.” 배우 리처드 버튼과 엘리자베스 테일러의 열정적인 러브 스토리에서 빠지지 않는 불가리 주얼리. 엘리자베스 테일러는 ‘세르펜티’ 컬렉션의 매력을 누구보다 먼저 알아봤고, 즐겨 착용했다. 마키즈 셰이프 브릴리언트 컷 다이아몬드, 페어 컷 에메랄드와 다이아몬드를 파베 세팅한 귀고리와 목걸이, 반지."
  }
]